README.md
setup.py
ParallelQueue.egg-info/PKG-INFO
ParallelQueue.egg-info/SOURCES.txt
ParallelQueue.egg-info/dependency_links.txt
ParallelQueue.egg-info/top_level.txt
parallelqueue/__init__.py
parallelqueue/arrivals.py
parallelqueue/base_models.py
parallelqueue/jobs.py
parallelqueue/monitors.py
parallelqueue/network.py
parallelqueue/routers.py