Metadata-Version: 2.1
Name: ParallelQueue
Version: 1.0.0
Summary: Parallel queueing models for SimPy
Home-page: https://github.com/aarjaneiro/ParallelQueue
Author: Aaron Janeiro Stone
Author-email: ajstone@uwaterloo.ca
License: MIT
Platform: UNKNOWN
